gh_analysis/__init__.py
gh_analysis/ai/__init__.py
gh_analysis/ai/agents.py
gh_analysis/ai/analysis.py
gh_analysis/ai/change_detector.py
gh_analysis/ai/comment_generator.py
gh_analysis/ai/image_utils.py
gh_analysis/ai/interactive.py
gh_analysis/ai/mcp_server.py
gh_analysis/ai/models.py
gh_analysis/ai/prompts.py
gh_analysis/ai/pydantic_ai_patch.py
gh_analysis/ai/settings_validator.py
gh_analysis/ai/troubleshooting_agents.py
gh_analysis/ai/batch/__init__.py
gh_analysis/ai/batch/batch_manager.py
gh_analysis/ai/batch/config_compat.py
gh_analysis/ai/batch/models.py
gh_analysis/ai/batch/openai_provider.py
gh_analysis/cli/__init__.py
gh_analysis/cli/batch.py
gh_analysis/cli/collect.py
gh_analysis/cli/export.py
gh_analysis/cli/main.py
gh_analysis/cli/options.py
gh_analysis/cli/process.py
gh_analysis/cli/recommendations.py
gh_analysis/cli/store_summary.py
gh_analysis/cli/update.py
gh_analysis/github_client/__init__.py
gh_analysis/github_client/attachments.py
gh_analysis/github_client/client.py
gh_analysis/github_client/models.py
gh_analysis/github_client/search.py
gh_analysis/recommendation/__init__.py
gh_analysis/recommendation/manager.py
gh_analysis/recommendation/models.py
gh_analysis/recommendation/review_session.py
gh_analysis/recommendation/status_tracker.py
gh_analysis/runners/__init__.py
gh_analysis/runners/adapters/__init__.py
gh_analysis/runners/adapters/mcp_adapter.py
gh_analysis/runners/base/__init__.py
gh_analysis/runners/base/product_labeling.py
gh_analysis/runners/specialized/__init__.py
gh_analysis/runners/specialized/product_agent.py
gh_analysis/runners/specialized/symptoms_agent.py
gh_analysis/runners/summary/__init__.py
gh_analysis/runners/summary/multi_summary.py
gh_analysis/runners/summary/summary_models.py
gh_analysis/runners/summary/summary_prompts.py
gh_analysis/runners/summary/specialized/__init__.py
gh_analysis/runners/summary/specialized/cause_agent.py
gh_analysis/runners/summary/specialized/confidence_agent.py
gh_analysis-0.9.0.dist-info/METADATA
gh_analysis-0.9.0.dist-info/WHEEL
gh_analysis-0.9.0.dist-info/entry_points.txt
gh_analysis-0.9.0.dist-info/RECORD
