Metadata-Version: 2.4
Name: gh-analysis
Version: 0.9.0
Summary: GitHub issue collection and AI-powered analysis
Requires-Python: >=3.13
Requires-Dist: anthropic>=0.7.0
Requires-Dist: cryptography==42.0.0
Requires-Dist: httpx>=0.24.0
Requires-Dist: mcp
Requires-Dist: openai>=1.99.3
Requires-Dist: openinference-instrumentation-pydantic-ai>=0.1.4
Requires-Dist: pydantic-ai>=1.2.1
Requires-Dist: pydantic>=2.5.0
Requires-Dist: pygithub>=2.6.1
Requires-Dist: python-dotenv>=1.0.0
Requires-Dist: requests>=2.32.4
Requires-Dist: rich>=13.0.0
Requires-Dist: slack-sdk>=3.33.0
Requires-Dist: snowflake-connector-python>=3.16.0
Requires-Dist: toml>=0.10.2
Requires-Dist: troubleshoot-mcp-server>=1.13.1
Requires-Dist: typer>=0.9.0
Provides-Extra: dev
Requires-Dist: mypy>=1.16.1; extra == 'dev'
Requires-Dist: pre-commit>=3.0.0; extra == 'dev'
Requires-Dist: pytest-asyncio>=1.0.0; extra == 'dev'
Requires-Dist: pytest-mock>=3.14.1; extra == 'dev'
Requires-Dist: pytest>=8.4.1; extra == 'dev'
Requires-Dist: ruff>=0.12.1; extra == 'dev'
Provides-Extra: export
Requires-Dist: pyyaml>=6.0.0; extra == 'export'
